huaweicloudsdklakeformation/__init__.py
huaweicloudsdklakeformation/v1/__init__.py
huaweicloudsdklakeformation/v1/lakeformation_async_client.py
huaweicloudsdklakeformation/v1/lakeformation_client.py
huaweicloudsdklakeformation/v1/model/__init__.py
huaweicloudsdklakeformation/v1/model/access_client_info.py
huaweicloudsdklakeformation/v1/model/access_client_request_body.py
huaweicloudsdklakeformation/v1/model/access_connection_info.py
huaweicloudsdklakeformation/v1/model/access_connection_request_body.py
huaweicloudsdklakeformation/v1/model/access_info.py
huaweicloudsdklakeformation/v1/model/access_policy_input.py
huaweicloudsdklakeformation/v1/model/access_request.py
huaweicloudsdklakeformation/v1/model/access_request_info.py
huaweicloudsdklakeformation/v1/model/access_service_info.py
huaweicloudsdklakeformation/v1/model/add_partition_input.py
huaweicloudsdklakeformation/v1/model/add_partitions_request.py
huaweicloudsdklakeformation/v1/model/add_partitions_response.py
huaweicloudsdklakeformation/v1/model/agency_request_body.py
huaweicloudsdklakeformation/v1/model/agreement_rule.py
huaweicloudsdklakeformation/v1/model/alter_partition_entry.py
huaweicloudsdklakeformation/v1/model/alter_partitions_input.py
huaweicloudsdklakeformation/v1/model/alter_role_input.py
huaweicloudsdklakeformation/v1/model/alter_table_input.py
huaweicloudsdklakeformation/v1/model/apply_for_access_request.py
huaweicloudsdklakeformation/v1/model/apply_for_access_response.py
huaweicloudsdklakeformation/v1/model/associate_principals_request.py
huaweicloudsdklakeformation/v1/model/associate_principals_response.py
huaweicloudsdklakeformation/v1/model/associate_roles_request.py
huaweicloudsdklakeformation/v1/model/associate_roles_response.py
huaweicloudsdklakeformation/v1/model/authorize_access_service_request.py
huaweicloudsdklakeformation/v1/model/authorize_access_service_response.py
huaweicloudsdklakeformation/v1/model/batch_authorize_interface_request.py
huaweicloudsdklakeformation-3.1.184.dist-info/METADATA
huaweicloudsdklakeformation-3.1.184.dist-info/WHEEL
huaweicloudsdklakeformation-3.1.184.dist-info/licenses/LICENSE
huaweicloudsdklakeformation-3.1.184.dist-info/RECORD
